<?xml version="1.0" encoding="UTF-8"?><record_update table="sp_instance">
    <sp_instance action="INSERT_OR_UPDATE">
        <active>true</active>
        <class_name/>
        <color>default</color>
        <css/>
        <glyph/>
        <id/>
        <order>2</order>
        <roles/>
        <short_description/>
        <size>md</size>
        <sp_column display_value="1">d8052bdddbbc13047e0ef2131f9619ca</sp_column>
        <sp_widget display_value="Meetup Attendee Checkin">2eba10d50f15270046c28b9ae1050e38</sp_widget>
        <sys_class_name>sp_instance</sys_class_name>
        <sys_created_by>daveslusher-sn</sys_created_by>
        <sys_created_on>2018-10-20 21:28:49</sys_created_on>
        <sys_id>78702c1d0f15270046c28b9ae1050ef6</sys_id>
        <sys_mod_count>0</sys_mod_count>
        <sys_name/>
        <sys_package display_value="Developer Meetup" source="x_snc_dev_meet">beeb33c5db7013047e0ef2131f961962</sys_package>
        <sys_policy/>
        <sys_scope display_value="Developer Meetup">beeb33c5db7013047e0ef2131f961962</sys_scope>
        <sys_update_name>sp_instance_78702c1d0f15270046c28b9ae1050ef6</sys_update_name>
        <sys_updated_by>daveslusher-sn</sys_updated_by>
        <sys_updated_on>2018-10-20 21:28:49</sys_updated_on>
        <title/>
        <url/>
        <widget_parameters/>
    </sp_instance>
    <sys_translated_text action="delete_multiple" query="documentkey=78702c1d0f15270046c28b9ae1050ef6"/>
</record_update>
